notion_gcal_sync/__init__.py
notion_gcal_sync/__main__.py
notion_gcal_sync/clients/GCalClient.py
notion_gcal_sync/clients/NotionClient.py
notion_gcal_sync/clients/__init__.py
notion_gcal_sync/config.py
notion_gcal_sync/core.py
notion_gcal_sync/events/Event.py
notion_gcal_sync/events/GCalEvent.py
notion_gcal_sync/events/NotionEvent.py
notion_gcal_sync/events/__init__.py
notion_gcal_sync/install.py
notion_gcal_sync/utils.py
notion_gcal_sync-1.1.12.dist-info/entry_points.txt
notion_gcal_sync-1.1.12.dist-info/LICENSE
notion_gcal_sync-1.1.12.dist-info/WHEEL
notion_gcal_sync-1.1.12.dist-info/METADATA
notion_gcal_sync-1.1.12.dist-info/RECORD
