Metadata-Version: 2.1
Name: notion-gcal-sync
Version: 1.1.12
Summary: Bidirectional synchronize calendar events within notion and google calendar
Home-page: https://github.com/Ravio1i/notion-gcal-sync
License: GNU General Public License v3.0
Author: Luka Kroeger
Author-email: luka.kroeger@gmail.com
Requires-Python: >=3.9,<4
Classifier: License :: Other/Proprietary License
Classifier: Programming Language :: Python :: 3
Classifier: Programming Language :: Python :: 3.10
Classifier: Programming Language :: Python :: 3.9
Requires-Dist: click (>=8.0.3,<9.0.0)
Requires-Dist: google-api-python-client (==2.23.0)
Requires-Dist: google-auth-oauthlib (==0.4.6)
Requires-Dist: notion-client (>=0.7.1,<0.8.0)
Requires-Dist: pandas (==1.3.3)
Requires-Dist: pendulum (>=2.1.2,<3.0.0)
Requires-Dist: pyyaml (==5.4.1)
Project-URL: Repository, https://github.com/Ravio1i/notion-gcal-sync
